tool_interface/__init__.py
tool_interface/_connections.py
tool_interface/config.py
tool_interface/datasets.py
tool_interface/health.py
tool_interface/models.py
tool_interface/storage.py
tool_interface-0.1.4.dist-info/METADATA
tool_interface-0.1.4.dist-info/WHEEL
tool_interface-0.1.4.dist-info/licenses/LICENSE
tool_interface-0.1.4.dist-info/RECORD
