Metadata-Version: 2.4
Name: tool_interface
Version: 0.1.4
Summary: Main Python package to access the 3DTrees backend from tool containers
Author: Mirko Mälicke
License:                     GNU GENERAL PUBLIC LICENSE
License-File: LICENSE
Requires-Python: >=3.9
Requires-Dist: aiobotocore
Requires-Dist: boto3
Requires-Dist: botocore
Requires-Dist: pydantic
Requires-Dist: pydantic-settings
Requires-Dist: python-dotenv>=1.1.0
Requires-Dist: s3fs
Requires-Dist: s3transfer
Requires-Dist: supabase
Provides-Extra: dev
Requires-Dist: mypy; extra == 'dev'
Requires-Dist: pre-commit; extra == 'dev'
Requires-Dist: pytest; extra == 'dev'
Requires-Dist: pytest-cov; extra == 'dev'
Requires-Dist: ruff; extra == 'dev'
